pike/__init__.py
pike/discovery/__init__.py
pike/discovery/filesystem.py
pike/discovery/py.py
pike/finder.py
pike/loader.py
pike/manager.py
pike-0.2.0.dist-info/LICENSE
pike-0.2.0.dist-info/METADATA
pike-0.2.0.dist-info/WHEEL
pike-0.2.0.dist-info/RECORD
