Metadata-Version: 2.1
Name: pike
Version: 0.2.0
Summary: Lightweight plugin management system for Python
License: Apache v2
Author: John Vrbanac
Author-email: john.vrbanac@linux.com
Requires-Python: >=3.7,<4.0
Classifier: License :: Other/Proprietary License
Classifier: Programming Language :: Python :: 3
Classifier: Programming Language :: Python :: 3.7
Classifier: Programming Language :: Python :: 3.8
Classifier: Programming Language :: Python :: 3.9
Classifier: Programming Language :: Python :: 3.10
Classifier: Programming Language :: Python :: 3.11
